{"type":"FeatureCollection","features":[{"type":"Feature","geometry":{"type":"Point","coordinates":[127.061835,37.623632]},"properties":{"station_cd":"1308","station_name":"광운대","station_fr_code":"P119"}},{"type":"Feature","geometry":{"type":"Point","coordinates":[127.085032,37.596362]},"properties":{"station_cd":"1309","station_name":"상봉","station_fr_code":"P120"}},{"type":"Feature","geometry":{"type":"Point","coordinates":[127.091909,37.59955]},"properties":{"station_cd":"1310","station_name":"망우","station_fr_code":"P121"}},{"type":"Feature","geometry":{"type":"Point","coordinates":[127.103218,37.612887]},"properties":{"station_cd":"1311","station_name":"신내","station_fr_code":"P122"}},{"type":"Feature","geometry":{"type":"Point","coordinates":[127.114757,37.634118]},"properties":{"station_cd":"1312","station_name":"갈매","station_fr_code":"P123"}},{"type":"Feature","geometry":{"type":"Point","coordinates":[127.12684,37.64202]},"properties":{"station_cd":"1313","station_name":"별내","station_fr_code":"P124"}},{"type":"Feature","geometry":{"type":"Point","coordinates":[127.143952,37.648311]},"properties":{"station_cd":"1314","station_name":"퇴계원","station_fr_code":"P125"}},{"type":"Feature","geometry":{"type":"Point","coordinates":[127.176933,37.65108]},"properties":{"station_cd":"1315","station_name":"사릉","station_fr_code":"P126"}},{"type":"Feature","geometry":{"type":"Point","coordinates":[127.207853,37.637382]},"properties":{"station_cd":"1316","station_name":"금곡","station_fr_code":"P127"}},{"type":"Feature","geometry":{"type":"Point","coordinates":[127.244493,37.653225]},"properties":{"station_cd":"1317","station_name":"평내호평","station_fr_code":"P128"}},{"type":"Feature","geometry":{"type":"Point","coordinates":[127.285379,37.658978]},"properties":{"station_cd":"1318","station_name":"천마산","station_fr_code":"P129"}},{"type":"Feature","geometry":{"type":"Point","coordinates":[127.311767,37.652782]},"properties":{"station_cd":"1319","station_name":"마석","station_fr_code":"P130"}},{"type":"Feature","geometry":{"type":"Point","coordinates":[127.379319,37.684071]},"properties":{"station_cd":"1320","station_name":"대성리","station_fr_code":"P131"}},{"type":"Feature","geometry":{"type":"Point","coordinates":[127.42661,37.735488]},"properties":{"station_cd":"1321","station_name":"청평","station_fr_code":"P132"}},{"type":"Feature","geometry":{"type":"Point","coordinates":[127.454821,37.770246]},"properties":{"station_cd":"1322","station_name":"상천","station_fr_code":"P133"}},{"type":"Feature","geometry":{"type":"Point","coordinates":[127.510739,37.814536]},"properties":{"station_cd":"1323","station_name":"가평","station_fr_code":"P134"}},{"type":"Feature","geometry":{"type":"Point","coordinates":[127.557695,37.832067]},"properties":{"station_cd":"1324","station_name":"굴봉산","station_fr_code":"P135"}},{"type":"Feature","geometry":{"type":"Point","coordinates":[127.58933,37.830779]},"properties":{"station_cd":"1325","station_name":"백양리","station_fr_code":"P136"}},{"type":"Feature","geometry":{"type":"Point","coordinates":[127.634146,37.805723]},"properties":{"station_cd":"1326","station_name":"강촌","station_fr_code":"P137"}},{"type":"Feature","geometry":{"type":"Point","coordinates":[127.71434,37.818466]},"properties":{"station_cd":"1327","station_name":"김유정","station_fr_code":"P138"}},{"type":"Feature","geometry":{"type":"Point","coordinates":[127.723792,37.864007]},"properties":{"station_cd":"1328","station_name":"남춘천","station_fr_code":"P139"}},{"type":"Feature","geometry":{"type":"Point","coordinates":[127.717023,37.885054]},"properties":{"station_cd":"1329","station_name":"춘천","station_fr_code":"P140"}}],"line":"G"}
